star_ratings/__init__.py
star_ratings/admin.py
star_ratings/app_settings.py
star_ratings/apps.py
star_ratings/checks.py
star_ratings/compat.py
star_ratings/forms.py
star_ratings/models.py
star_ratings/signals.py
star_ratings/urls.py
star_ratings/views.py
star_ratings/locale/de/LC_MESSAGES/django.mo
star_ratings/locale/de/LC_MESSAGES/django.po
star_ratings/locale/eu/LC_MESSAGES/django.mo
star_ratings/locale/eu/LC_MESSAGES/django.po
star_ratings/locale/fr/LC_MESSAGES/django.mo
star_ratings/locale/fr/LC_MESSAGES/django.po
star_ratings/locale/it/LC_MESSAGES/django.mo
star_ratings/locale/it/LC_MESSAGES/django.po
star_ratings/locale/pt_BR/LC_MESSAGES/django.mo
star_ratings/locale/pt_BR/LC_MESSAGES/django.po
star_ratings/locale/ru/LC_MESSAGES/django.mo
star_ratings/locale/ru/LC_MESSAGES/django.po
star_ratings/migrations/0001_initial.py
star_ratings/migrations/0002_auto_20160608_1119.py
star_ratings/migrations/0003_auto_20160721_1127.py
star_ratings/migrations/__init__.py
star_ratings/static/star-ratings/config.rb
star_ratings/static/star-ratings/css/star-ratings.css
star_ratings/static/star-ratings/images/admin_stars.png
star_ratings/static/star-ratings/images/stars.png
star_ratings/static/star-ratings/js/index.js
star_ratings/static/star-ratings/js/dist/.gitkeep
star_ratings/static/star-ratings/js/dist/star-ratings.js
star_ratings/static/star-ratings/js/dist/star-ratings.min.js
star_ratings/static/star-ratings/js/src/ratings.js
star_ratings/static/star-ratings/js/src/rest.js
star_ratings/static/star-ratings/js/src/utils.js
star_ratings/static/star-ratings/sass/star-ratings.scss
star_ratings/templates/admin/includes/_rating_stars.html
star_ratings/templates/star_ratings/widget.html
star_ratings/templates/star_ratings/widget_base.html
star_ratings/templatetags/__init__.py
star_ratings/templatetags/ratings.py
tests/__init__.py
tests/base.py
tests/conftest.py
tests/fakes.py
tests/models.py
tests/strategies.py
tests/test_app_settings.py
tests/test_rating.py
django_star_ratings-0.9.2.dist-info/LICENSE
django_star_ratings-0.9.2.dist-info/METADATA
django_star_ratings-0.9.2.dist-info/WHEEL
django_star_ratings-0.9.2.dist-info/top_level.txt
django_star_ratings-0.9.2.dist-info/RECORD
