Metadata-Version: 2.1
Name: django-star-ratings
Version: 0.9.2
Summary: A Django app to add star ratings to models.
Home-page: https://github.com/wildfish/django-star-ratings
Author: Wildfish
Author-email: developers@wildfish.com
License: BSD License
Keywords: ratings
Platform: UNKNOWN
Classifier: Development Status :: 4 - Beta
Classifier: Environment :: Web Environment
Classifier: Framework :: Django
Classifier: License :: OSI Approved :: BSD License
Classifier: Operating System :: OS Independent
Classifier: Programming Language :: Python
Classifier: Programming Language :: Python :: 3
Classifier: Programming Language :: Python :: 3.6
Classifier: Programming Language :: Python :: 3.7
Classifier: Programming Language :: Python :: 3.8
License-File: LICENSE
